{
  "version": "20.0.0",
  "files": {
    "ce013d47e81e42cadfc8207383fc893802cd090768e4b863ad50045d34680d25": {
      "source": {
        "path": "CdkServerStack.template.json",
        "packaging": "file"
      },
      "destinations": {
        "current_account-current_region": {
          "bucketName": "cdk-hnb659fds-assets-${AWS::AccountId}-${AWS::Region}",
          "objectKey": "ce013d47e81e42cadfc8207383fc893802cd090768e4b863ad50045d34680d25.json",
          "assumeRoleArn": "arn:${AWS::Partition}:iam::${AWS::AccountId}:role/cdk-hnb659fds-file-publishing-role-${AWS::AccountId}-${AWS::Region}"
        }
      }
    }
  },
  "dockerImages": {}
}